LICENSE
MANIFEST.in
README.md
requirements.txt
setup.py
personaldata/__init__.py
personaldata/base.py
personaldata/chess_statistics.py
personaldata/getwebsite.py
personaldata/github_statistics.py
personaldata.egg-info/PKG-INFO
personaldata.egg-info/SOURCES.txt
personaldata.egg-info/dependency_links.txt
personaldata.egg-info/requires.txt
personaldata.egg-info/top_level.txt
tests/__init__.py
tests/test_chess.py
tests/test_github.py