Metadata-Version: 2.1
Name: personaldata
Version: 0.0.3
Summary: personaldata Python package
Author: zosialaa
Author-email: zofia.lapinska@gmail.com
Keywords: python,personaldata
Classifier: Programming Language :: Python :: 3
License-File: LICENSE
